galaxywitness/__init__.py
galaxywitness/__main__.py
galaxywitness/alpha_complex.py
galaxywitness/ansi.txt
galaxywitness/ansiname.txt
galaxywitness/base_complex.py
galaxywitness/clusterization.py
galaxywitness/datasets.py
galaxywitness/manual_density.py
galaxywitness/rips_complex.py
galaxywitness/tests/test_betti.py
galaxywitness/tests/test_tomato.py
galaxywitness/witness_complex.py
galaxywitness-0.2.4.dist-info/LICENSE
galaxywitness-0.2.4.dist-info/METADATA
galaxywitness-0.2.4.dist-info/WHEEL
galaxywitness-0.2.4.dist-info/RECORD
