Metadata-Version: 2.1
Name: galaxywitness
Version: 0.2.4
Summary: Package for topological data analysis of the big data. It is attempt to study distribution of galaxies in the universe via TDA
Home-page: https://github.com/davidosx/GalaxyWitness
License: MIT
Author: David Miheev
Author-email: me@davidkorol.life
Requires-Python: >=3.8
Classifier: License :: OSI Approved :: MIT License
Classifier: Programming Language :: Python :: 3
Classifier: Programming Language :: Python :: 3.8
Classifier: Programming Language :: Python :: 3.9
Classifier: Programming Language :: Python :: 3.10
Classifier: Programming Language :: Python :: 3.11
Requires-Dist: astropy
Requires-Dist: gudhi
Requires-Dist: matplotlib
Requires-Dist: numpy
Requires-Dist: pandas
Requires-Dist: plotly
Requires-Dist: prompt-toolkit
Requires-Dist: pyvo
Requires-Dist: scikit-learn
Requires-Dist: tqdm
Project-URL: Documentation, https://galaxywitness.rtfd.io/
Project-URL: Repository, https://github.com/davidosx/GalaxyWitness
